opender/__init__.py
opender/capability_and_priority.py
opender/der.py
opender/der_bess.py
opender/der_pv.py
opender/op_cond_proc.py
opender/output_options.py
opender/rt_perf.py
opender/setting_execution_delay.py
opender/Parameters/AS-with std-values.csv
opender/Parameters/Model-parameters.csv
opender/active_power_support_funcs/__init__.py
opender/active_power_support_funcs/active_power_limit.py
opender/active_power_support_funcs/es_perf.py
opender/active_power_support_funcs/frequency_droop.py
opender/active_power_support_funcs/frequency_droop_bess.py
opender/active_power_support_funcs/p_funcs.py
opender/active_power_support_funcs/p_funcs_bess.py
opender/active_power_support_funcs/p_funcs_pv.py
opender/active_power_support_funcs/volt_watt.py
opender/auxiliary_funcs/__init__.py
opender/auxiliary_funcs/cond_delay.py
opender/auxiliary_funcs/flipflop.py
opender/auxiliary_funcs/low_pass_filter.py
opender/auxiliary_funcs/ramping.py
opender/auxiliary_funcs/sym_component.py
opender/auxiliary_funcs/time_delay.py
opender/bess_specifc/__init__.py
opender/bess_specifc/bess_specific.py
opender/bess_specifc/soc.py
opender/common_file_format/__init__.py
opender/common_file_format/common_file_format.py
opender/common_file_format/common_file_format_BESS.py
opender/operation_status/__init__.py
opender/operation_status/operating_status.py
opender/operation_status/operating_status_pv.py
opender/operation_status/rt_crit.py
opender/operation_status/enter_service_crit/__init__.py
opender/operation_status/enter_service_crit/es_crit.py
opender/operation_status/enter_service_crit/es_crit_pv.py
opender/operation_status/trip_crit/__init__.py
opender/operation_status/trip_crit/trip_crit.py
opender/operation_status/trip_crit/trip_crit_pv.py
opender/reactive_power_support_funcs/__init__.py
opender/reactive_power_support_funcs/constant_pf.py
opender/reactive_power_support_funcs/constant_vars.py
opender/reactive_power_support_funcs/q_funcs.py
opender/reactive_power_support_funcs/volt_var.py
opender-2.2.0.dist-info/LICENSE.txt
opender-2.2.0.dist-info/METADATA
opender-2.2.0.dist-info/WHEEL
opender-2.2.0.dist-info/top_level.txt
opender-2.2.0.dist-info/RECORD
