Metadata-Version: 2.1
Name: opender
Version: 2.2.0
Summary: Open-source Distributed Energy Resources (DER) Model that represents IEEE Standard 1547-2018 requirements for steady-state and dynamic analyses
Home-page: https://github.com/epri-dev/opender
Author: Yiwei Ma, Wei Ren, Paulo Radatz, Jithendar Anandan
Author-email: yma@epri.com, wren@epri.com, pradatz@epri.com
License: BSD
Project-URL: Homepage, https://www.epri.com/OpenDER
Project-URL: Model Specification, https://www.epri.com/research/products/000000003002030962
Classifier: Development Status :: 4 - Beta
Classifier: Intended Audience :: Developers
Classifier: License :: OSI Approved :: BSD License
Classifier: Operating System :: Microsoft :: Windows
Classifier: Programming Language :: Python :: 3.7
Classifier: Topic :: Utilities
Requires-Python: >=3.7
License-File: LICENSE.txt
Requires-Dist: numpy
Requires-Dist: matplotlib
Requires-Dist: pandas
Provides-Extra: dev
Requires-Dist: pytest ; extra == 'dev'
Requires-Dist: pytest-cov ; extra == 'dev'
